setup.py
nova/AnsysDD_sketch.py
nova/CuCrZr_SDC_IC.py
nova/DD_coils.py
nova/DD_first_wall.py
nova/DD_streamfunction.py
nova/DD_volume_ratio.py
nova/DDmove.py
nova/DDplot.py
nova/GD_tmp.py
nova/Jscript_funcions.py
nova/Jscript_functions.py
nova/Pshape.py
nova/Ptools.py
nova/RBconfig.py
nova/RK_tmp.py
nova/SFcomp.py
nova/SX_swing_contors.py
nova/TF_vol.py
nova/__init__.py
nova/addtext.py
nova/ansys_coils.py
nova/beam_calc.py
nova/bndry_rms.py
nova/check_elliptic.py
nova/coil_core.py
nova/coil_dl.py
nova/coil_force.py
nova/coil_force_vectors.py
nova/coil_forces.py
nova/coil_geometory.py
nova/coil_locations.py
nova/coil_pair.py
nova/coils.py
nova/compare_SX.py
nova/compare_firstwalls.py
nova/config.py
nova/connection3D.py
nova/connection_plot.py
nova/connection_profiles.py
nova/connection_profiles_data_comp.py
nova/cross_coil.py
nova/cross_coil_old.py
nova/deap_tmp.py
nova/debugGS.py
nova/divertor_rad.py
nova/double_coil.py
nova/double_decker_radial_build.py
nova/elliptic.py
nova/eq_write.py
nova/eqconfig.py
nova/eqlib.py
nova/export_sol.py
nova/extract.py
nova/feild_calc.py
nova/filters.py
nova/fit.py
nova/flux_fit.py
nova/flux_functions.py
nova/force_elliptic.py
nova/force_swing.py
nova/frame_writer.py
nova/geqdsk.py
nova/import_eqlib.py
nova/in_plasma.py
nova/interpolate_psi_grid.py
nova/inverse.py
nova/inverse_power.py
nova/line_intergral.py
nova/load_eqdsk.py
nova/load_eqdsk_tripple.py
nova/load_eqlib.py
nova/load_history.py
nova/moveP6.py
nova/moveSXcoils.py
nova/moveSXcoils_051015.py
nova/moveXcoils.py
nova/moveXcoils_old (2).py
nova/moveXcoils_old.py
nova/old_plasma_parameters.py
nova/plasma_coil_current.py
nova/plasma_coils.py
nova/plasma_contor.py
nova/plasma_equlibrium.py
nova/plasma_para.py
nova/plasma_parameters.py
nova/plasma_parameters_double.py
nova/plasma_parameters_double2.py
nova/plasma_shape.py
nova/plot_SX.py
nova/plot_force_swing.py
nova/plot_opp.py
nova/png_tools.py
nova/png_tools_old.py
nova/prototypes.py
nova/pymls.py
nova/radial_build.py
novastella.egg-info/PKG-INFO
novastella.egg-info/SOURCES.txt
novastella.egg-info/dependency_links.txt
novastella.egg-info/not-zip-safe
novastella.egg-info/top_level.txt