Metadata-Version: 1.0
Name: novastella
Version: 0.0.1
Summary: equlibrium tools
Home-page: https://github.com/twistersi/Nova
Author: Simon McIntosh
Author-email: simon.mcintosh@ukaea.uk
License: MIT
Platform: UNKNOWN
